{
  "version": "7",
  "dialect": "postgresql",
  "entries": [
    {
      "idx": 0,
      "version": "7",
      "when": 1782921804843,
      "tag": "0000_dark_spitfire",
      "breakpoints": true
    },
    {
      "idx": 1,
      "version": "7",
      "when": 1782925593009,
      "tag": "0001_majestic_dracula",
      "breakpoints": true
    },
    {
      "idx": 2,
      "version": "7",
      "when": 1783020000000,
      "tag": "0002_location_output_stations",
      "breakpoints": true
    },
    {
      "idx": 3,
      "version": "7",
      "when": 1783023600000,
      "tag": "0003_output_station_capabilities",
      "breakpoints": true
    },
    {
      "idx": 4,
      "version": "7",
      "when": 1783059311816,
      "tag": "0004_shallow_jackpot",
      "breakpoints": true
    }
  ]
}
